kvcopy/__init__.py
kvcopy-2.0.0.dist-info/LICENSE
kvcopy-2.0.0.dist-info/METADATA
kvcopy-2.0.0.dist-info/WHEEL
kvcopy-2.0.0.dist-info/entry_points.txt
kvcopy-2.0.0.dist-info/RECORD
